LICENSE
MANIFEST.in
README.rst
setup.py
django_simple_sso.hga.egg-info/PKG-INFO
django_simple_sso.hga.egg-info/SOURCES.txt
django_simple_sso.hga.egg-info/dependency_links.txt
django_simple_sso.hga.egg-info/not-zip-safe
django_simple_sso.hga.egg-info/requires.txt
django_simple_sso.hga.egg-info/top_level.txt
simple_sso/__init__.py
simple_sso/models.py
simple_sso/settings.py
simple_sso/signals.py
simple_sso/utils.py
simple_sso/sso_client/__init__.py
simple_sso/sso_client/apps.py
simple_sso/sso_client/client.py
simple_sso/sso_client/middleware.py
simple_sso/sso_server/__init__.py
simple_sso/sso_server/apps.py
simple_sso/sso_server/models.py
simple_sso/sso_server/server.py
simple_sso/sso_server/migrations/0001_initial.py
simple_sso/sso_server/migrations/0002_consumer_name_max_length.py
simple_sso/sso_server/migrations/0003_token_session.py
simple_sso/sso_server/migrations/__init__.py
tests/__init__.py
tests/settings.py
tests/test_core.py
tests/test_migrations.py
tests/urls.py
tests/utils/__init__.py
tests/utils/context_managers.py